awsjavakit_cfn_rules/__init__.py
awsjavakit_cfn_rules/rules/__init__.py
awsjavakit_cfn_rules/rules/__pycache__/__init__.cpython-313.pyc
awsjavakit_cfn_rules/rules/__pycache__/batch_job_definition_log_rule.cpython-313.pyc
awsjavakit_cfn_rules/rules/__pycache__/lambda_listens_to_event_bridge.cpython-313.pyc
awsjavakit_cfn_rules/rules/__pycache__/sqs_long_polling_rule.cpython-313.pyc
awsjavakit_cfn_rules/rules/__pycache__/tags_checker.cpython-313.pyc
awsjavakit_cfn_rules/rules/batch_job_definition_log_rule.py
awsjavakit_cfn_rules/rules/lambda_listens_to_event_bridge.py
awsjavakit_cfn_rules/rules/sqs_long_polling_rule.py
awsjavakit_cfn_rules/rules/tags_checker.py
awsjavakit_cfn_rules/utils/__pycache__/functional.cpython-313.pyc
awsjavakit_cfn_rules/utils/__pycache__/invalid_config_exception.cpython-313.pyc
awsjavakit_cfn_rules/utils/functional.py
awsjavakit_cfn_rules/utils/invalid_config_exception.py
awsjavakit_cfn_rules-0.0.38.dist-info/METADATA
awsjavakit_cfn_rules-0.0.38.dist-info/WHEEL
awsjavakit_cfn_rules-0.0.38.dist-info/RECORD
