Metadata-Version: 2.1
Name: awsjavakit-cfn-rules
Version: 0.0.38
Summary: Extendable CFN rules
Author: Orestis Gkorgkas
Author-email: orestis.gorgas@gmail.com
Requires-Python: >=3.10.15,<4.0.0
Classifier: Programming Language :: Python :: 3
Classifier: Programming Language :: Python :: 3.11
Classifier: Programming Language :: Python :: 3.12
Classifier: Programming Language :: Python :: 3.13
Requires-Dist: attrs (==24.2.0)
Requires-Dist: cfn-lint (>=1.42.1,<2.0.0)
